<?xml version="1.0" encoding="UTF-8"?>
<record_update table="ua_table_licensing_config">
    <ua_table_licensing_config action="INSERT_OR_UPDATE">
        <is_fulfillment>false</is_fulfillment>
        <name>x_72724_trainbook_login</name>
        <owner_condition table="x_72724_trainbook_login">sys_created_by=javascript:gs.getUserName()^EQ<item endquery="false" field="sys_created_by" goto="false" newquery="false" operator="=" or="false" value="javascript:gs.getUserName()"/>
            <item endquery="true" field="" goto="false" newquery="false" operator="=" or="false" value=""/>
        </owner_condition>
        <sys_class_name>ua_table_licensing_config</sys_class_name>
        <sys_created_by>admin</sys_created_by>
        <sys_created_on>2016-09-22 18:29:36</sys_created_on>
        <sys_customer_update>true</sys_customer_update>
        <sys_id>89529419db862600cb44f00fbf9619fd</sys_id>
        <sys_mod_count>0</sys_mod_count>
        <sys_name>x_72724_trainbook_login</sys_name>
        <sys_package display_value="trainbook" source="x_72724_trainbook">4b4ca789db462600cb44f00fbf961932</sys_package>
        <sys_policy/>
        <sys_replace_on_upgrade>false</sys_replace_on_upgrade>
        <sys_scope display_value="trainbook">4b4ca789db462600cb44f00fbf961932</sys_scope>
        <sys_update_name>ua_table_licensing_config_89529419db862600cb44f00fbf9619fd</sys_update_name>
        <sys_updated_by>admin</sys_updated_by>
        <sys_updated_on>2016-09-22 18:29:36</sys_updated_on>
    </ua_table_licensing_config>
</record_update>
